pywe_qrcode/__init__.py
pywe_qrcode/pyqrcode.py
pywe_qrcode-1.0.3.dist-info/METADATA
pywe_qrcode-1.0.3.dist-info/WHEEL
pywe_qrcode-1.0.3.dist-info/top_level.txt
pywe_qrcode-1.0.3.dist-info/RECORD
